agentflowz/__init__.py
agentflowz/main.py
agentflowz-0.1.2.dist-info/METADATA
agentflowz-0.1.2.dist-info/WHEEL
agentflowz-0.1.2.dist-info/top_level.txt
agentflowz-0.1.2.dist-info/RECORD
