Metadata-Version: 2.4
Name: agentflowz
Version: 0.1.2
Summary: Add your description here
Requires-Python: >=3.10
Requires-Dist: dotenv>=0.9.9
Requires-Dist: llama-index>=0.12.40
Requires-Dist: llama-index-core>=0.12.40
